nns/__init__.py
nns/imagenet_input.py
nns/model_def.py
nns/models.py
nns/nas_utils.py
nns/parse_netarch.py
nns/preprocessing.py
nns/singlepath_supernet.py
nns/spn_runtime_model.json
nns/superkernel.py
nns/supernet_macro.py
nns/utils.py
nod_labs_NNS-0.0.1.dist-info/METADATA
nod_labs_NNS-0.0.1.dist-info/WHEEL
nod_labs_NNS-0.0.1.dist-info/top_level.txt
nod_labs_NNS-0.0.1.dist-info/RECORD
