Metadata-Version: 2.1
Name: nod-labs-NNS
Version: 0.0.1
Summary: Nod AutoML package for neural architecture search and model training of image classification
Home-page: https://nod.com
Author: Nod Labs
Author-email: bingyu@nod-labs.com
License: UNKNOWN
Platform: UNKNOWN
Classifier: Programming Language :: Python :: 3
Classifier: License :: OSI Approved :: MIT License
Classifier: Operating System :: OS Independent
Requires-Python: >=3.5
